docsplit/VERSION
docsplit/__init__.py
docsplit/config.py
docsplit/converters/__init__.py
docsplit/converters/image_converter.py
docsplit/converters/merge_converter.py
docsplit/converters/pdf_converter.py
docsplit/handlers/__init__.py
docsplit/handlers/document_splitter.py
docsplit/utils/__init__.py
docsplit/utils/helpers.py
docsplit-0.1.2.dist-info/METADATA
docsplit-0.1.2.dist-info/WHEEL
docsplit-0.1.2.dist-info/top_level.txt
docsplit-0.1.2.dist-info/RECORD
